{"href": "https://brainly.com/question/7695909", "domain": "brainly.com", "source": "com", "time": 1530241633855, "brainly_data": {"question": "History !!!!!!!!!!!!!!!!", "subject": "History", "date": "1513194227", "all_answers": [{"question": "History !!!!!!!!!!!!!!!!", "subject": "History", "text": "\n1: Pulpit\n2: Presbyterian\n3: Pietist\n4: Steal\n5: Ticonderoga\n6: Riot\n7: Teenager\n8: Seal\n9: Treaty of Ulrecht\n\n:)\n", "rating": 5, "reputation": "Ambitious", "num_upvotes": 2, "num_thanks": 4}, {"question": "History !!!!!!!!!!!!!!!!", "subject": "History", "text": "\n1) Pulpit\n2) Presbyterian\n3) Pietist\n4) Steal\n5) Ticonderoga\n6) Riot\n7) Teenager\n8) Seal\n9) Treaty of Ulrecht\n\nHope this helps! :)\u00a0\n\n\n", "rating": 5, "reputation": "Beginner", "num_upvotes": 1, "num_thanks": 3}], "top_answer": {"question": "History !!!!!!!!!!!!!!!!", "subject": "History", "text": "\n1: Pulpit\n2: Presbyterian\n3: Pietist\n4: Steal\n5: Ticonderoga\n6: Riot\n7: Teenager\n8: Seal\n9: Treaty of Ulrecht\n\n:)\n", "rating": 5, "reputation": "Ambitious", "num_upvotes": 2, "num_thanks": 4}}, "availability": {"url": "https://brainly.com", "archived_snapshots": {"closest": {"status": "200", "available": true, "url": "http://web.archive.org/web/20180624052629/https://brainly.com/", "timestamp": "20180624052629"}}}}